officekit/__init__.py
officekit/address_formats.py
officekit/admin_urls.py
officekit/apps.py
officekit/blocks.py
officekit/default_settings.py
officekit/frontend.py
officekit/mixins.py
officekit/model_porter.py
officekit/models.py
officekit/permissions.py
officekit/wagtail_hooks.py
officekit/widgets.py
officekit/migrations/0001_initial.py
officekit/migrations/0002_add_address_formats.py
officekit/migrations/__init__.py
officekit/static/officekit/css/group_blocks.css
officekit/static/officekit/css/group_layout.css
officekit/templates/officekit/blocks/formatted_address_block.html
officekit/templates/officekit/blocks/group_assignment_list_block.html
officekit/templates/officekit/blocks/group_list_block.html
officekit/templates/officekit/blocks/group_member_list_block.html
officekit/templates/officekit/blocks/group_member_list_switch.html
officekit/templates/officekit/blocks/name_list_block.html
officekit/templates/officekit/tags/support.html
officekit/templatetags/__init__.py
officekit/templatetags/officekit_tags.py
officekit/views/__init__.py
officekit/views/chooser.py
officekit/viewsets/__init__.py
officekit/viewsets/chooser.py
officekit-4.1.0.dist-info/AUTHORS.txt
officekit-4.1.0.dist-info/LICENSE.txt
officekit-4.1.0.dist-info/METADATA
officekit-4.1.0.dist-info/WHEEL
officekit-4.1.0.dist-info/top_level.txt
officekit-4.1.0.dist-info/zip-safe
officekit-4.1.0.dist-info/RECORD
