Metadata-Version: 2.1
Name: officekit
Version: 4.1.0
Summary: A Wagtail app providing models for people, teams, addresses and other office-related entities.
Home-page: https://github.com/high-dimensional/officekit
Author: High Dimensional Neurology Group, UCL
Author-email: pypi@highdimensional.net
License: BSD-3-Clause
Platform: any
Classifier: Framework :: Django
Classifier: Framework :: Wagtail
Classifier: Programming Language :: Python :: 3
Classifier: Programming Language :: Python :: 3.8
Classifier: License :: OSI Approved :: BSD License
Classifier: Operating System :: OS Independent
Requires-Python: >=3.8
License-File: LICENSE.txt
License-File: AUTHORS.txt
Requires-Dist: Django (<4.2,>=4.1)
Requires-Dist: wagtail (<4.2,>=4.1)
Requires-Dist: django-countries (<7.5,>=7.4)
Requires-Dist: steadfast (<1.1,>=1.0)
Requires-Dist: csskit (<1.1,>=1.0)
Requires-Dist: django-auxiliaries (<4.2,>=4.1)
Requires-Dist: model-porter (<4.2,>=4.1)
Requires-Dist: wagtail-switch-block (<4.2,>=4.1)
Requires-Dist: wagtail-block-model-field (<4.2,>=4.1)
Requires-Dist: wagtail-association-panel (<4.2,>=4.1)
Requires-Dist: wagtail-dynamic-choice (<4.2,>=4.1)
Requires-Dist: wagtail-richer-text (<4.2,>=4.1)
Requires-Dist: tour-guide (<4.2,>=4.1)
Requires-Dist: aldine (<4.2,>=4.1.1)
Requires-Dist: media-catalogue (<4.2,>=4.1.2)
Requires-Dist: figurative (<4.2,>=4.1)
Requires-Dist: querykit (<4.2,>=4.1)
